cell2sentence/__init__.py
cell2sentence/csdata.py
cell2sentence/csmodel.py
cell2sentence/prompt_formatter.py
cell2sentence/tasks.py
cell2sentence/utils.py
cell2sentence/prompts/__init__.py
cell2sentence/prompts/multi_cell_natural_lang_interpretation_prompts.json
cell2sentence/prompts/multi_cell_tissue_conditional_generation.json
cell2sentence/prompts/multi_cell_tissue_prediction_prompts.json
cell2sentence/prompts/single_cell_cell_type_conditional_generation_prompts.json
cell2sentence/prompts/single_cell_cell_type_prediction_prompts.json
cell2sentence-1.2.0.dist-info/LICENSE
cell2sentence-1.2.0.dist-info/METADATA
cell2sentence-1.2.0.dist-info/WHEEL
cell2sentence-1.2.0.dist-info/top_level.txt
cell2sentence-1.2.0.dist-info/RECORD
