Metadata-Version: 2.1
Name: cell2sentence
Version: 1.2.0
Summary: Cell2Sentence: Single-cell Analysis With LLMs
Home-page: https://github.com/vandijklab/cell2sentence
Author: Syed Asad Rizvi
Author-email: syed.rizvi@yale.edu
License: 'BY-NC-ND'
Project-URL: Bug Tracker, https://github.com/vandijklab/cell2sentence/issues
Classifier: Programming Language :: Python :: 3
Classifier: Development Status :: 2 - Pre-Alpha
Classifier: Operating System :: OS Independent
Requires-Python: >=3.7
License-File: LICENSE
Requires-Dist: torch
Requires-Dist: transformers
Requires-Dist: datasets
Requires-Dist: anndata
Requires-Dist: scanpy
Requires-Dist: numpy
Requires-Dist: pandas
Requires-Dist: scipy
Requires-Dist: tqdm
Requires-Dist: scikit-learn
Requires-Dist: jupyterlab
Requires-Dist: accelerate
Requires-Dist: plotnine
Requires-Dist: sphinx
Requires-Dist: sphinx-rtd-theme
